[
	{
		"node-category" : "DataObject",
		"action" : 
		{
			"verb" : "create",
			"content" :
			{
					"storageType" : "DL", 
					"displayName" : "MCT Session", 
					"description"	: "MCT Session aggrregated data",
					"name" : "MCT_SESSION",
					"product" : "ATT"
					"type" : "parquet",
					"partitionType" : "none"
			},
			"schema" : 
			{
					"type" : "struct",
					"fields" : [ {
						"name" : "TRANSFER_END_TS",
						"type" : "string",
						"nullable" : true,
						"metadata" : { }
					}, {
						"name" : "SOURCE_CARRIER_ID",
						"type" : "string",
						"nullable" : true,
						"metadata" : { }
					}, {
						"name" : "SOURCE_MANUFACTURER",
						"type" : "string",
						"nullable" : true,
						"metadata" : { }
					}, {
						"name" : "SIZE_BUCKET_SORT",
						"type" : "double",
						"nullable" : true,
						"metadata" : { }
					}, {
						"name" : "AVAILABLE_ITEMS",
						"type" : "long",
						"nullable" : true,
						"metadata" : { }
					}, {
						"name" : "TRANSFER_SECONDS",
						"type" : "double",
						"nullable" : true,
						"metadata" : { }
					}, {
						"name" : "TRANSFER_ITEMS",
						"type" : "long",
						"nullable" : true,
						"metadata" : { }
					}, {
						"name" : "DURATION_BUCKET_SORT",
						"type" : "double",
						"nullable" : true,
						"metadata" : { }
					}, {
						"name" : "SOURCE_MODEL",
						"type" : "string",
						"nullable" : true,
						"metadata" : { }
					}, {
						"name" : "TARGET_ACTIVECARRIERID",
						"type" : "string",
						"nullable" : true,
						"metadata" : { }
					}, {
						"name" : "LINK_SPEED",
						"type" : "double",
						"nullable" : true,
						"metadata" : { }
					}, {
						"name" : "TRANSFER_BYTES",
						"type" : "double",
						"nullable" : true,
						"metadata" : { }
					}, {
						"name" : "HAS_MUSIC",
						"type" : "string",
						"nullable" : true,
						"metadata" : { }
					}, {
						"name" : "SELECTED_ITEMS",
						"type" : "long",
						"nullable" : true,
						"metadata" : { }
					}, {
						"name" : "AVAILABLE_BYTES",
						"type" : "double",
						"nullable" : true,
						"metadata" : { }
					}, {
						"name" : "FAILED_ITEMS",
						"type" : "long",
						"nullable" : true,
						"metadata" : { }
					}, {
						"name" : "SOURCE_DEVICE_ID",
						"type" : "string",
						"nullable" : true,
						"metadata" : { }
					}, {
						"name" : "ERROR_COUNT",
						"type" : "long",
						"nullable" : true,
						"metadata" : { }
					}, {
						"name" : "SOURCE_INTERNALVERSION",
						"type" : "string",
						"nullable" : true,
						"metadata" : { }
					}, {
						"name" : "HAS_DOCUMENTS",
						"type" : "string",
						"nullable" : true,
						"metadata" : { }
					}, {
						"name" : "HAS_MESSAGES",
						"type" : "string",
						"nullable" : true,
						"metadata" : { }
					}, {
						"name" : "OPCO",
						"type" : "string",
						"nullable" : true,
						"metadata" : { }
					}, {
						"name" : "SESSION_STATUS",
						"type" : "string",
						"nullable" : true,
						"metadata" : { }
					}, {
						"name" : "TARGET_MANUFACTURER",
						"type" : "string",
						"nullable" : true,
						"metadata" : { }
					}, {
						"name" : "TARGET_OS",
						"type" : "string",
						"nullable" : true,
						"metadata" : { }
					}, {
						"name" : "SELECTED_BYTES",
						"type" : "double",
						"nullable" : true,
						"metadata" : { }
					}, {
						"name" : "TARGET_APP_VERSION",
						"type" : "string",
						"nullable" : true,
						"metadata" : { }
					}, {
						"name" : "TRANSFER_METHOD",
						"type" : "string",
						"nullable" : true,
						"metadata" : { }
					}, {
						"name" : "SUMMARY_TYPE",
						"type" : "string",
						"nullable" : true,
						"metadata" : { }
					}, {
						"name" : "HAS_CALL_LOGS",
						"type" : "string",
						"nullable" : true,
						"metadata" : { }
					}, {
						"name" : "TARGET_INTERNALVERSION",
						"type" : "string",
						"nullable" : true,
						"metadata" : { }
					}, {
						"name" : "SERVER_TIMESTAMP",
						"type" : "string",
						"nullable" : true,
						"metadata" : { }
					}, {
						"name" : "SOURCE_APP_VERSION",
						"type" : "string",
						"nullable" : true,
						"metadata" : { }
					}, {
						"name" : "HAS_IMAGES",
						"type" : "string",
						"nullable" : true,
						"metadata" : { }
					}, {
						"name" : "AVAILABLE_MB",
						"type" : "double",
						"nullable" : true,
						"metadata" : { }
					}, {
						"name" : "MSISDN",
						"type" : "string",
						"nullable" : true,
						"metadata" : { }
					}, {
						"name" : "HAS_OTHER",
						"type" : "string",
						"nullable" : true,
						"metadata" : { }
					}, {
						"name" : "SERVER_MONTH",
						"type" : "string",
						"nullable" : true,
						"metadata" : { }
					}, {
						"name" : "TARGET_MODEL",
						"type" : "string",
						"nullable" : true,
						"metadata" : { }
					}, {
						"name" : "QUARATINE_CODE",
						"type" : "long",
						"nullable" : true,
						"metadata" : { }
					}, {
						"name" : "TARGET_DEVICE_ID",
						"type" : "string",
						"nullable" : true,
						"metadata" : { }
					}, {
						"name" : "SOURCE_OS",
						"type" : "string",
						"nullable" : true,
						"metadata" : { }
					}, {
						"name" : "LINK_TYPE",
						"type" : "string",
						"nullable" : true,
						"metadata" : { }
					}, {
						"name" : "TARGET_CARRIER_ID",
						"type" : "string",
						"nullable" : true,
						"metadata" : { }
					}, {
						"name" : "IMSI",
						"type" : "string",
						"nullable" : true,
						"metadata" : { }
					}, {
						"name" : "TRANSFER_LOCATION",
						"type" : "string",
						"nullable" : true,
						"metadata" : { }
					}, {
						"name" : "SIZE_BUCKET",
						"type" : "string",
						"nullable" : true,
						"metadata" : { }
					}, {
						"name" : "SSID",
						"type" : "string",
						"nullable" : true,
						"metadata" : { }
					}, {
						"name" : "ICCID",
						"type" : "string",
						"nullable" : true,
						"metadata" : { }
					}, {
						"name" : "HAS_VIDEOS",
						"type" : "string",
						"nullable" : true,
						"metadata" : { }
					}, {
						"name" : "TRANSFER_MINUTES",
						"type" : "double",
						"nullable" : true,
						"metadata" : { }
					}, {
						"name" : "DURATION_BUCKET",
						"type" : "string",
						"nullable" : true,
						"metadata" : { }
					}, {
						"name" : "HAS_CONTACTS",
						"type" : "string",
						"nullable" : true,
						"metadata" : { }
					}, {
						"name" : "IMEI",
						"type" : "string",
						"nullable" : true,
						"metadata" : { }
					}, {
						"name" : "CHANNEL_WIDTH",
						"type" : "double",
						"nullable" : true,
						"metadata" : { }
					}, {
						"name" : "SOURCE_ACTIVECARRIERID",
						"type" : "string",
						"nullable" : true,
						"metadata" : { }
					}, {
						"name" : "TIME_LINE_DAYS",
						"type" : "string",
						"nullable" : true,
						"metadata" : { }
					}, {
						"name" : "FAILED_BYTES",
						"type" : "double",
						"nullable" : true,
						"metadata" : { }
					}, {
						"name" : "SOURCE_TIMEZONE",
						"type" : "string",
						"nullable" : true,
						"metadata" : { }
					}, {
						"name" : "TRANSFER_START_TS",
						"type" : "string",
						"nullable" : true,
						"metadata" : { }
					}, {
						"name" : "TRANSFER_MB",
						"type" : "double",
						"nullable" : true,
						"metadata" : { }
					}, {
						"name" : "FAILED_MB",
						"type" : "double",
						"nullable" : true,
						"metadata" : { }
					}, {
						"name" : "TARGET_TIMEZONE",
						"type" : "string",
						"nullable" : true,
						"metadata" : { }
					}, {
						"name" : "IN_STORE_TRANSFER",
						"type" : "string",
						"nullable" : true,
						"metadata" : { }
					}, {
						"name" : "FATAL_ERROR_FLAG",
						"type" : "string",
						"nullable" : true,
						"metadata" : { }
					}, {
						"name" : "TRANSFER_TYPE",
						"type" : "string",
						"nullable" : true,
						"metadata" : { }
					}, {
						"name" : "SESSION_ID",
						"type" : "string",
						"nullable" : true,
						"metadata" : { }
					} ]
				}
			"dl-locations" : [ 
				"/mapr/bda_lab_batch/dl.dev/data/mct/output/MCT_SESSION"
			]
		}
	}
]
		